iam_explorer/__init__.py
iam_explorer/cli.py
iam_explorer/fetch.py
iam_explorer/graph.py
iam_explorer/query.py
iam_explorer/utils.py
iam_explorer/visualize.py
iam_explorer-1.17.1.dist-info/LICENSE
iam_explorer-1.17.1.dist-info/METADATA
iam_explorer-1.17.1.dist-info/WHEEL
iam_explorer-1.17.1.dist-info/entry_points.txt
iam_explorer-1.17.1.dist-info/top_level.txt
iam_explorer-1.17.1.dist-info/RECORD
