Metadata-Version: 2.1
Name: iam-explorer
Version: 1.17.1
Summary: A CLI tool to visualize AWS IAM relationships and answer permission queries
Author-email: Safouene Gharbi <gharbi.safwen@hotmail.com>
License: Apache License
Classifier: Programming Language :: Python :: 3.10
Classifier: Programming Language :: Python :: 3.11
Classifier: Programming Language :: Python :: 3.12
Classifier: Programming Language :: Python :: 3.13
Classifier: Programming Language :: Python :: 3 :: Only
Classifier: License :: OSI Approved :: Apache Software License
Requires-Python: <4.0,>=3.10
License-File: LICENSE
Requires-Dist: boto3>=1.20.0
Requires-Dist: graphviz>=0.20
Requires-Dist: networkx>=3.4
Requires-Dist: click>=8.0
Provides-Extra: dev
Requires-Dist: pytest>=8.3; extra == "dev"
Requires-Dist: pytest-cov>=6.0; extra == "dev"
Requires-Dist: black>=24.1; extra == "dev"
Requires-Dist: flake8>=7.0; extra == "dev"
Requires-Dist: moto>=5.0; extra == "dev"
